Workbook

Sheet README
A1: Sunshine Group (KSF) vs Vingroup (VIC) - credit comparison for KRW bond (Arirang) analysis
A2: Units: VND billion unless stated. Fiscal year ending 31 Dec. Both: consolidated, Vietnamese Accounting Standards.
A3: Sources: Vingroup Annual Report 2025 (EY audited, MD&A tables + FS); Sunshine Group Annual Report 2025 (Deloitte audited, FS read from scanned pages).
A4: Blue font = hard-coded input from source. Black = formula. Yellow fill = ASSUMPTION to be replaced (not from a filing).
A5: Sheets: Data (inputs) -> Ratios (formulas) -> Collateral (LTV calculator) -> Flags (diligence points).
A6: EBITDA is analyst-defined: Profit before tax + interest expense + D&A. 'Adj. EBITDA' also removes 'other profit/(loss)' (non-operating).
A7: Caution: Sunshine statements were read visually from low-resolution scans; spot-check key lines against the audited originals before external use.
A8: Not yet in the model: the KED article terms (coupon, tenor, security) - could not be accessed; Vingroup bond terms from press only.

Sheet Data
A1: Item | B1: Unit | C1: Vingroup FY2025 | D1: Vingroup FY2024 | E1: Sunshine FY2025 | F1: Sunshine FY2024 | G1: Source / note
A2: Net revenue | B2: VND bn | C2: 331838 | D2: 189068 | E2: 20198.17 | F2: 2469.47 | G2: Vin: AR MD&A; Sun: income statement
A3: Gross profit | B3: VND bn | C3: 52682.807 | D3: 27300.818 | E3: 13135.92 | F3: 1234.81 | G3: Vin: income stmt (VND m /1000); Sun: income stmt
A4: Operating profit (net) | B4: VND bn | C4: 7937 | D4: 11665 | E4: 11408.49 | F4: 973.68 | G4: As reported (Vin 'Net operating profit')
A5: Other profit / (loss) | B5: VND bn | C5: 18500 | D5: 5074 | E5: -114.01 | F5: 0.73 | G5: Non-operating; Vin 2025 is large
A6: Profit before tax | B6: VND bn | C6: 26437 | D6: 16739 | E6: 11294.49 | F6: 974.41
A7: Profit after tax | B7: VND bn | C7: 11065 | D7: 5276 | E7: 8906.22 | F7: 773.85
A8: Interest expense (incl. issuance costs) | B8: VND bn | C8: 29159.736 | D8: 22980.044 | E8: 663.98 | F8: 142.63 | G8: Income stmt; may exclude capitalised interest
A9: Depreciation & amortisation | B9: VND bn | C9: 31665.247 | D9: 22627.124 | E9: 51.02 | F9: 40.1 | G9: Vin: note 'Depreciation, amortisation and allocation of goodwill'; Sun: cash flow
A10: Current assets | B10: VND bn | C10: 658772 | D10: 396480 | E10: 81393.56 | F10: 13425.28
A11: Non-current assets | B11: VND bn | C11: 459850 | D11: 440124 | E11: 38750.11 | F11: 7133.06
A12: Total assets | B12: VND bn | C12: 1118623 | D12: 836604 | E12: 120143.67 | F12: 20558.34
A13: Cash & cash equivalents | B13: VND bn | C13: 73542.242 | D13: 42582.366 | E13: 4800.84 | F13: 386.04
A14: Short-term receivables | B14: VND bn | C14: n/a | D14: n/a | E14: 57697.02 | F14: 9322.89 | G14: Sun only (48% of assets) - see Flags
A15: Inventories | B15: VND bn | C15: n/a | D15: n/a | E15: 14687.12 | F15: 865.69 | G15: Sun only
A16: Current liabilities | B16: VND bn | C16: 587455 | D16: 505292 | E16: 52774.31 | F16: 8570.72
A17: Total liabilities | B17: VND bn | C17: 967134 | D17: 682769 | E17: 100280.4 | F17: 13679.09
A18: Total borrowings & finance leases | B18: VND bn | C18: 338501 | D18: 227920 | E18: 23623.44 | F18: 946.49 | G18: Sun = ST 9,159.8 + LT 14,463.6 (notes 27/28 lines)
A19: Advances from customers (ST) | B19: VND bn | C19: n/a | D19: n/a | E19: 24556.05 | F19: 5677.62 | G19: Sun only; deferred revenue-type liability
A20: Total equity (incl. NCI) | B20: VND bn | C20: 151489 | D20: 153834 | E20: 19863.27 | F20: 6879.24
A21: Net cash from operating activities | B21: VND bn | C21: n/a | D21: n/a | E21: 23314.99 | F21: 5375.15 | G21: Sun CFO inflated by customer deposits - see Flags
A22: Net cash from investing activities | B22: VND bn | C22: n/a | D22: n/a | E22: -15267.42 | F22: -3313.19
A23: Net cash from financing activities | B23: VND bn | C23: n/a | D23: n/a | E23: -3632.77 | F23: -1847.06

Sheet Ratios
A1: Metric | B1: Vingroup FY2025 | C1: Vingroup FY2024 | D1: Sunshine FY2025 | E1: Sunshine FY2024 | F1: Comment
A2: SCALE
A3: Total assets (VND bn) | B3: =Data!C12 | C3: =Data!D12 | D3: =Data!E12 | E3: =Data!F12
A4: Net revenue (VND bn) | B4: =Data!C2 | C4: =Data!D2 | D4: =Data!E2 | E4: =Data!F2
A5: Equity (VND bn) | B5: =Data!C20 | C5: =Data!D20 | D5: =Data!E20 | E5: =Data!F20
A6: PROFITABILITY
A7: Gross margin | B7: =Data!C3/Data!C2 | C7: =Data!D3/Data!D2 | D7: =Data!E3/Data!E2 | E7: =Data!F3/Data!F2 | F7: Sunshine margin reflects land/plot transfers
A8: Net margin (PAT/revenue) | B8: =Data!C7/Data!C2 | C8: =Data!D7/Data!D2 | D8: =Data!E7/Data!E2 | E8: =Data!F7/Data!F2
A9: ROE (PAT / year-end equity) | B9: =Data!C7/Data!C20 | C9: =Data!D7/Data!D20 | D9: =Data!E7/Data!E20 | E9: =Data!F7/Data!F20 | F9: Sun flattered by low equity base and one-off scale-up
A10: ROA (PAT / year-end assets) | B10: =Data!C7/Data!C12 | C10: =Data!D7/Data!D12 | D10: =Data!E7/Data!E12 | E10: =Data!F7/Data!F12
A11: EBITDA (PBT+interest+D&A) | B11: =Data!C6+Data!C8+Data!C9 | C11: =Data!D6+Data!D8+Data!D9 | D11: =Data!E6+Data!E8+Data!E9 | E11: =Data!F6+Data!F8+Data!F9
A12: Adj. EBITDA (excl. other profit) | B12: =Data!C6+Data!C8+Data!C9-Data!C5 | C12: =Data!D6+Data!D8+Data!D9-Data!D5 | D12: =Data!E6+Data!E8+Data!E9-Data!E5 | E12: =Data!F6+Data!F8+Data!F9-Data!F5
A13: LEVERAGE
A14: Total liabilities / total assets | B14: =Data!C17/Data!C12 | C14: =Data!D17/Data!D12 | D14: =Data!E17/Data!E12 | E14: =Data!F17/Data!F12 | F14: Both very high; includes customer deposits
A15: Total liabilities / equity (x) | B15: =Data!C17/Data!C20 | C15: =Data!D17/Data!D20 | D15: =Data!E17/Data!E20 | E15: =Data!F17/Data!F20 | F15: Sunshine report shows 5.05x; Vin 6.4x
A16: Borrowings / equity (x) | B16: =Data!C18/Data!C20 | C16: =Data!D18/Data!D20 | D16: =Data!E18/Data!E20 | E16: =Data!F18/Data!F20
A17: Borrowings / total assets | B17: =Data!C18/Data!C12 | C17: =Data!D18/Data!D12 | D17: =Data!E18/Data!E12 | E17: =Data!F18/Data!F12
A18: Net debt (borrowings - cash) (VND bn) | B18: =Data!C18-Data!C13 | C18: =Data!D18-Data!D13 | D18: =Data!E18-Data!E13 | E18: =Data!F18-Data!F13 | F18: Cash & equivalents only
A19: Net debt / Adj. EBITDA (x) | B19: =(Data!C18-Data!C13)/(Data!C6+Data!C8+Data!C9-Data!C5) | C19: =(Data!D18-Data!D13)/(Data!D6+Data!D8+Data!D9-Data!D5) | D19: =(Data!E18-Data!E13)/(Data!E6+Data!E8+Data!E9-Data!E5) | E19: =(Data!F18-Data!F13)/(Data!F6+Data!F8+Data!F9-Data!F5) | F19: Key credit metric for bond investors
A20: Net debt / EBITDA (x) | B20: =(Data!C18-Data!C13)/(Data!C6+Data!C8+Data!C9) | C20: =(Data!D18-Data!D13)/(Data!D6+Data!D8+Data!D9) | D20: =(Data!E18-Data!E13)/(Data!E6+Data!E8+Data!E9) | E20: =(Data!F18-Data!F13)/(Data!F6+Data!F8+Data!F9)
A21: COVERAGE & LIQUIDITY
A22: EBITDA / interest expense (x) | B22: =(Data!C6+Data!C8+Data!C9)/Data!C8 | C22: =(Data!D6+Data!D8+Data!D9)/Data!D8 | D22: =(Data!E6+Data!E8+Data!E9)/Data!E8 | E22: =(Data!F6+Data!F8+Data!F9)/Data!F8 | F22: Sun interest may exclude capitalised interest
A23: Adj. EBITDA / interest expense (x) | B23: =(Data!C6+Data!C8+Data!C9-Data!C5)/Data!C8 | C23: =(Data!D6+Data!D8+Data!D9-Data!D5)/Data!D8 | D23: =(Data!E6+Data!E8+Data!E9-Data!E5)/Data!E8 | E23: =(Data!F6+Data!F8+Data!F9-Data!F5)/Data!F8
A24: Current ratio (x) | B24: =Data!C10/Data!C16 | C24: =Data!D10/Data!D16 | D24: =Data!E10/Data!E16 | E24: =Data!F10/Data!F16
A25: Cash / current liabilities | B25: =Data!C13/Data!C16 | C25: =Data!D13/Data!D16 | D25: =Data!E13/Data!E16 | E25: =Data!F13/Data!F16
A26: Implied interest rate (interest / year-end debt) | B26: =Data!C8/Data!C18 | C26: =Data!D8/Data!D18 | D26: =Data!E8/Data!E18 | E26: =Data!F8/Data!F18 | F26: Understates for Sun (debt jumped in-year)
A28: GROWTH (FY2025 vs FY2024)
A29: Revenue growth | B29: =Data!C2/Data!D2-1 | D29: =Data!E2/Data!F2-1
A30: Total assets growth | B30: =Data!C12/Data!D12-1 | D30: =Data!E12/Data!F12-1 | F30: Sunshine step-change in one year = limited track record
A31: Borrowings growth | B31: =Data!C18/Data!D18-1 | D31: =Data!E18/Data!F18-1
A32: Equity growth | B32: =Data!C20/Data!D20-1 | D32: =Data!E20/Data!F20-1
A34: SIZE RELATIVE
A35: Sunshine assets as % of Vingroup | D35: =Data!E12/Data!C12
A36: Sunshine revenue as % of Vingroup | D36: =Data!E2/Data!C2
A37: Sunshine borrowings as % of Vingroup | D37: =Data!E18/Data!C18

Sheet Collateral
A1: Land collateral / LTV calculator (Ciputra, Hanoi) - ALL YELLOW CELLS ARE PLACEHOLDERS
A3: Bond size (KRW bn) | B3: 400 | C3: Assumption: matches Vingroup Arirang deal (~KRW 400bn; board approval up to 455bn). Replace with Sunshine's target.
A4: FX: VND per 1 KRW | B4: 18 | C4: ASSUMPTION - replace with current rate
A5: Appraised value of pledged land (VND bn) | B5: 10000 | C5: PLACEHOLDER - need independent valuation
A6: Valuation haircut (forced-sale discount) | B6: 0.3 | C6: ASSUMPTION
A7: Existing senior liens on same land (VND bn) | B7: 0 | C7: UNKNOWN - Sunshine notes show Ciputra/Nam Thang Long project assets already pledged to banks (see Flags)
A8: Target max LTV (bond / haircut value) | B8: 0.6 | C8: ASSUMPTION - typical secured structure range 50-70%
A11: CALCULATIONS
A12: Bond size (VND bn) | B12: =B3*B4 | C12: KRW bn x VND per KRW = VND bn (e.g. 300 x 18 = 5,400)
A13: Haircut collateral value (VND bn) | B13: =B5*(1-B6)
A14: Net collateral value after existing liens (VND bn) | B14: =MAX(B13-B7,0)
A15: LTV = bond / net collateral value | B15: =IF(B14=0,"n/a",B12/B14)
A16: Collateral coverage (x) = net collateral / bond | B16: =IF(B12=0,"n/a",B14/B12)
A17: Minimum collateral needed for target LTV (VND bn, haircut basis) | B17: =B12/B8+B7
A18: Minimum APPRAISED value needed (VND bn) | B18: =B17/(1-B6) | C18: Give this number to the valuer / client
A19: Pass target LTV? | B19: =IF(B15="n/a","n/a",IF(B15<=B8,"YES","NO"))
A21: Sensitivity: LTV by appraised value (rows) and haircut (columns); existing liens and bond size from above
A22: Appraised value (VND bn) | B22: 0.2 | C22: 0.3 | D22: 0.4 | E22: 0.5
A23: 6000 | B23: =IF(($A23*(1-B$22)-$B$7)<=0,"n/a",$B$12/($A23*(1-B$22)-$B$7)) | C23: =IF(($A23*(1-C$22)-$B$7)<=0,"n/a",$B$12/($A23*(1-C$22)-$B$7)) | D23: =IF(($A23*(1-D$22)-$B$7)<=0,"n/a",$B$12/($A23*(1-D$22)-$B$7)) | E23: =IF(($A23*(1-E$22)-$B$7)<=0,"n/a",$B$12/($A23*(1-E$22)-$B$7))
A24: 8000 | B24: =IF(($A24*(1-B$22)-$B$7)<=0,"n/a",$B$12/($A24*(1-B$22)-$B$7)) | C24: =IF(($A24*(1-C$22)-$B$7)<=0,"n/a",$B$12/($A24*(1-C$22)-$B$7)) | D24: =IF(($A24*(1-D$22)-$B$7)<=0,"n/a",$B$12/($A24*(1-D$22)-$B$7)) | E24: =IF(($A24*(1-E$22)-$B$7)<=0,"n/a",$B$12/($A24*(1-E$22)-$B$7))
A25: 10000 | B25: =IF(($A25*(1-B$22)-$B$7)<=0,"n/a",$B$12/($A25*(1-B$22)-$B$7)) | C25: =IF(($A25*(1-C$22)-$B$7)<=0,"n/a",$B$12/($A25*(1-C$22)-$B$7)) | D25: =IF(($A25*(1-D$22)-$B$7)<=0,"n/a",$B$12/($A25*(1-D$22)-$B$7)) | E25: =IF(($A25*(1-E$22)-$B$7)<=0,"n/a",$B$12/($A25*(1-E$22)-$B$7))
A26: 12000 | B26: =IF(($A26*(1-B$22)-$B$7)<=0,"n/a",$B$12/($A26*(1-B$22)-$B$7)) | C26: =IF(($A26*(1-C$22)-$B$7)<=0,"n/a",$B$12/($A26*(1-C$22)-$B$7)) | D26: =IF(($A26*(1-D$22)-$B$7)<=0,"n/a",$B$12/($A26*(1-D$22)-$B$7)) | E26: =IF(($A26*(1-E$22)-$B$7)<=0,"n/a",$B$12/($A26*(1-E$22)-$B$7))
A27: 15000 | B27: =IF(($A27*(1-B$22)-$B$7)<=0,"n/a",$B$12/($A27*(1-B$22)-$B$7)) | C27: =IF(($A27*(1-C$22)-$B$7)<=0,"n/a",$B$12/($A27*(1-C$22)-$B$7)) | D27: =IF(($A27*(1-D$22)-$B$7)<=0,"n/a",$B$12/($A27*(1-D$22)-$B$7)) | E27: =IF(($A27*(1-E$22)-$B$7)<=0,"n/a",$B$12/($A27*(1-E$22)-$B$7))
A28: 20000 | B28: =IF(($A28*(1-B$22)-$B$7)<=0,"n/a",$B$12/($A28*(1-B$22)-$B$7)) | C28: =IF(($A28*(1-C$22)-$B$7)<=0,"n/a",$B$12/($A28*(1-C$22)-$B$7)) | D28: =IF(($A28*(1-D$22)-$B$7)<=0,"n/a",$B$12/($A28*(1-D$22)-$B$7)) | E28: =IF(($A28*(1-E$22)-$B$7)<=0,"n/a",$B$12/($A28*(1-E$22)-$B$7))

Sheet Flags
A1: # | B1: Topic | C1: Finding | D1: Why it matters to a Korean investor | E1: Action
A2: 1 | B2: Track record / scale jump | C2: Sunshine total assets VND 20.6tn -> 120.1tn (+484%); revenue 2.5tn -> 20.2tn (+718%) in one year. | D2: Limited history at current scale; 2025 may reflect consolidation of acquired entities. Investors discount un-seasoned growth. | E2: Reconcile via notes: which subsidiaries were consolidated in 2025 and when.
A3: 2 | B3: Receivables concentration | C3: Short-term receivables VND 57.7tn = 48% of total assets (loans receivable 19.9tn, other receivables 23.2tn, supplier advances 13.3tn). | D3: Counterparty / related-party credit risk; recoverability underpins equity. | E3: Obtain counterparty breakdown, related-party disclosure, ageing, collateral held.
A4: 3 | B4: Auditor emphasis of matter | C4: Deloitte: unmodified opinion with emphasis on extended terms of loan agreements and investment cooperation contracts (Notes 10, 11). | D4: Signals receivables are being rolled over; a classic credit flag. | E4: Read Notes 10-11 in full; quantify extended balances.
A5: 4 | B5: Earnings quality | C5: 94.8% of revenue (VND 19.1tn) from real-estate transfers; net margin 44% vs Vin 3.3%. | D5: Lumpy, project-timing driven; not a recurring earnings base. | E5: Get 2026 handover pipeline; stress-test EBITDA at lower handovers.
A6: 5 | B6: Operating cash flow distorted | C6: CFO +23.3tn includes deposits received 18.6tn and is offset by deposits paid for share transfers 17.4tn (in 'other' operating lines). | D6: CFO is not a clean measure of debt service capacity. | E6: Rebuild a clean cash-flow bridge excluding deposits.
A7: 6 | B7: Debt rose without matching cash flow | C7: Borrowings 0.9tn -> 23.6tn, but cash flow shows proceeds 9.3tn vs repayments 12.9tn. | D7: Debt came largely from consolidation of acquired entities (non-cash). | E7: Confirm via acquisition notes; get a post-acquisition debt schedule.
A8: 7 | B8: Interest cost low vs debt | C8: Interest expense VND 664bn on 23.6tn year-end debt = ~2.8% (understated; debt jumped in-year; possible capitalisation). | D8: EBITDA/interest of ~18x may be flattering. | E8: Get capitalised interest (note on CIP/inventory) and pro-forma full-year interest.
A9: 8 | B9: Ciputra land already encumbered | C9: Debt note shows a VND 5,788bn HDBank loan to Wonderland Real Estate JSC secured on Sunshine Crystal Tay Ho project (Nam Thang Long / Ciputra urban area) plus project rights, accounts and shares. (Read from rotated scan - verify.) | D9: Land offered to bondholders may already be pledged; priority of lien decides recovery. | E9: Obtain land-use certificates, mortgage registry extract, and bank consent / release plan.
A10: 9 | B10: Is Vingroup secured? | C10: Vingroup board resolution of 11 Aug 2026 (up to KRW 455bn, 3 years, coupon cap 8%) is reported as secured by 4 outlets; CafeF says unsecured. Pledged assets not disclosed. | D10: Premise 'Vin unsecured' is probably wrong; a secured Sunshine bond is in line with the benchmark. Collateral quality and priority are what differentiate. | E10: Get the original Vingroup resolution / HOSE disclosure and the Korean offering memorandum for the security package.
A11: 10 | B11: Foreign-currency & legal | C11: KRW bond: FX risk (KRW vs VND/USD), enforceability of Vietnamese land lien for foreign bondholders (security agent), approvals for foreign borrowing, withholding tax. | D11: Structural/legal items decide whether collateral is real protection. | E11: Engage Vietnamese counsel; confirm security-agent structure used in comparable deals.
A12: 11 | B12: Auditors differ | C12: Vingroup: Ernst & Young Vietnam. Sunshine: Deloitte Vietnam. Both Big-4. | D12: Comparable audit quality; no discount either way. | E12: -
